picoh/MotorDefinitionsPicoh.omd
picoh/PicohSettings.xml
picoh/PicohSpeech.csv
picoh/Silence1.wav
picoh/__init__.py
picoh/ohbot.obe
picoh/picoh.py
picoh/Images/calibrate2400.gif
picoh/Images/calibrate400.gif
picoh/Images/logoPT.gif
picoh/Images/movedown.gif
picoh/Images/moveright.gif
picoh/Images/off.gif
picoh/Images/offsmaller.gif
picoh/Images/on.gif
picoh/Images/onsmaller.gif
picoh/Images/picohlogo.gif
picoh/Images/picohlogoOn.gif
picoh/Images/picohlogoSmall.gif
picoh/Images/pixel.gif
picoh/Images/plus.gif
picoh/Images/resetIcon.gif
picoh/Images/savebutton.gif
picoh/Sounds/fanfare.wav
picoh/Sounds/loop.wav
picoh/Sounds/ohbot.wav
picoh/Sounds/smash.wav
picoh/Sounds/spring.wav
picoh-1.276.dist-info/METADATA
picoh-1.276.dist-info/WHEEL
picoh-1.276.dist-info/top_level.txt
picoh-1.276.dist-info/RECORD
